[
    {
        "timestamp": "2024-10-14 10:51:01 PM",
        "User": "edith start to data visualizations",
        "AI": "Let's get started on the data visualizations, sir. What type of visualization would you like me to create? A graph, chart, or perhaps an interactive dashboard?"
    },
    {
        "timestamp": "2024-10-14 10:52:45 PM",
        "User": "edith start data of conciliation",
        "AI": "Sir, the system's uptime is approximately 49 minutes. Would you like me to retrieve any specific details from this information?"
    },
    {
        "timestamp": "2024-10-15 07:07:43 PM",
        "User": "edith open mouthe asks",
        "AI": "Sir, I'm ready to assist. What would you like me to focus on next?"
    },
    {
        "timestamp": "2024-10-21 08:51:39 PM",
        "User": "edith what time is it",
        "AI": "Sir, the current time is 20:50."
    },
    {
        "timestamp": "2024-10-22 05:28:01 PM",
        "User": "edith what times it h",
        "AI": "Sir, the current time is 17:27."
    }
]